README.md
setup.py
ATD/ATD.py
ATD/__init__.py
atdapi.egg-info/PKG-INFO
atdapi.egg-info/SOURCES.txt
atdapi.egg-info/dependency_links.txt
atdapi.egg-info/not-zip-safe
atdapi.egg-info/top_level.txt